{
 "generated": "2026-06-19 10:12Z",
 "source": "scirate.com",
 "windows": {
  "today": {
   "papers": [
    {
     "id": "2606.19482",
     "title": "Nearest-neighbour gates are all you need: High-rate quantum low-density parity-check codes on a planar grid",
     "scites": 90
    },
    {
     "id": "2606.20263",
     "title": "Vine Codes: Low-Overhead Quantum LDPC Codes on a Planar Square Grid",
     "scites": 62
    },
    {
     "id": "2606.20535",
     "title": "Near-Optimal Learning of Local Lindbladians",
     "scites": 36
    },
    {
     "id": "2606.19486",
     "title": "Optimal Ansatz-free Hamiltonian Learning In Situ",
     "scites": 36
    },
    {
     "id": "2606.20513",
     "title": "Approximating optimal decoding of quantum LDPC codes with narrow frontiers",
     "scites": 23
    },
    {
     "id": "2606.20472",
     "title": "Many-body chirality of topological stabilizer states",
     "scites": 14
    },
    {
     "id": "2606.20344",
     "title": "Quantum ring all-reduce: communication and privacy advantages for distributed learning",
     "scites": 13
    },
    {
     "id": "2606.20551",
     "title": "Benchmark of quantum algorithms for ground state preparation in the presence of noise",
     "scites": 12
    },
    {
     "id": "2606.20003",
     "title": "Optimal Shadow Estimation with Minimal Measurement Settings",
     "scites": 12
    },
    {
     "id": "2606.19873",
     "title": "Random Local Stabilizer Codes in Three Dimensions without String or Self-Similar Fractal Logical Operators",
     "scites": 12
    }
   ],
   "keywords": [
    {
     "word": "codes planar",
     "papers": 2,
     "scites": 152,
     "score": 83
    },
    {
     "word": "quantum ldpc",
     "papers": 2,
     "scites": 85,
     "score": 61
    },
    {
     "word": "ldpc codes",
     "papers": 2,
     "scites": 85,
     "score": 61
    },
    {
     "word": "quantum algorithms",
     "papers": 3,
     "scites": 25,
     "score": 58
    },
    {
     "word": "state preparation",
     "papers": 2,
     "scites": 16,
     "score": 39
    },
    {
     "word": "variational quantum",
     "papers": 2,
     "scites": 4,
     "score": 35
    }
   ]
  },
  "week": {
   "papers": [
    {
     "id": "2606.18188",
     "title": "Learning Arbitrary Lindbladians with Quantum Error Correction",
     "scites": 109
    },
    {
     "id": "2606.19482",
     "title": "Nearest-neighbour gates are all you need: High-rate quantum low-density parity-check codes on a planar grid",
     "scites": 90
    },
    {
     "id": "2606.18145",
     "title": "A polynomial-time approximation scheme for minimum-weight decoding of topological codes",
     "scites": 70
    },
    {
     "id": "2606.18515",
     "title": "Exponentially many initializations to avoid barren plateaus",
     "scites": 63
    },
    {
     "id": "2606.16712",
     "title": "Complete entanglement detection using polynomial invariants",
     "scites": 63
    },
    {
     "id": "2606.20263",
     "title": "Vine Codes: Low-Overhead Quantum LDPC Codes on a Planar Square Grid",
     "scites": 62
    },
    {
     "id": "2606.18035",
     "title": "Approximately Decoding the Colour Code",
     "scites": 49
    },
    {
     "id": "2606.16425",
     "title": "Worst-case depth hierarchy for shallow quantum circuits",
     "scites": 49
    },
    {
     "id": "2606.13779",
     "title": "Computational regimes in matrix-product-state-based quantum trajectory simulations",
     "scites": 45
    },
    {
     "id": "2606.17268",
     "title": "Breaking the bicycle frame: Coset-based quantum LDPC codes",
     "scites": 41
    }
   ],
   "keywords": [
    {
     "word": "quantum error",
     "papers": 5,
     "scites": 166,
     "score": 100
    },
    {
     "word": "error correction",
     "papers": 5,
     "scites": 166,
     "score": 100
    },
    {
     "word": "quantum ldpc",
     "papers": 4,
     "scites": 139,
     "score": 82
    },
    {
     "word": "ldpc codes",
     "papers": 4,
     "scites": 139,
     "score": 82
    },
    {
     "word": "codes planar",
     "papers": 2,
     "scites": 152,
     "score": 66
    },
    {
     "word": "quantum computing",
     "papers": 3,
     "scites": 52,
     "score": 46
    },
    {
     "word": "topological codes",
     "papers": 2,
     "scites": 78,
     "score": 43
    },
    {
     "word": "optimal decoding",
     "papers": 2,
     "scites": 51,
     "score": 35
    }
   ]
  },
  "month": {
   "papers": [
    {
     "id": "2606.11484",
     "title": "Handbook of Error-Correcting Codes",
     "scites": 194
    },
    {
     "id": "2605.29137",
     "title": "Quantum error correction and fault tolerance: A comprehensive tutorial",
     "scites": 184
    },
    {
     "id": "2605.21457",
     "title": "An Exponential Sample-Complexity Advantage for Coherent Quantum Inference",
     "scites": 181
    },
    {
     "id": "2605.21898",
     "title": "Concatenating Algebraic Codes over High-Rate Quantum LDPC Codes",
     "scites": 127
    },
    {
     "id": "2606.06455",
     "title": "Breakeven demonstration of quantum low-density parity-check codes",
     "scites": 122
    },
    {
     "id": "2606.12363",
     "title": "Fermions are fundamentally more nonlocal than Bosons",
     "scites": 115
    },
    {
     "id": "2605.30455",
     "title": "A Denser Planar Surface Code",
     "scites": 110
    },
    {
     "id": "2606.18188",
     "title": "Learning Arbitrary Lindbladians with Quantum Error Correction",
     "scites": 109
    },
    {
     "id": "2605.31544",
     "title": "More efficient Clifford+T synthesis for small-angle rotations and application to Trotterization",
     "scites": 101
    },
    {
     "id": "2606.08349",
     "title": "Quantum algorithms for stochastic nonlinear differential equations",
     "scites": 98
    }
   ],
   "keywords": [
    {
     "word": "quantum error",
     "papers": 5,
     "scites": 473,
     "score": 100
    },
    {
     "word": "error correction",
     "papers": 4,
     "scites": 415,
     "score": 84
    },
    {
     "word": "quantum ldpc",
     "papers": 4,
     "scites": 306,
     "score": 72
    },
    {
     "word": "ldpc codes",
     "papers": 4,
     "scites": 306,
     "score": 72
    },
    {
     "word": "magic state",
     "papers": 3,
     "scites": 155,
     "score": 46
    },
    {
     "word": "fault tolerance",
     "papers": 2,
     "scites": 228,
     "score": 44
    },
    {
     "word": "high-rate quantum",
     "papers": 2,
     "scites": 217,
     "score": 43
    },
    {
     "word": "quantum low-density",
     "papers": 2,
     "scites": 212,
     "score": 42
    }
   ]
  },
  "year": {
   "papers": [
    {
     "id": "2604.07639",
     "title": "Exponential quantum advantage in processing massive classical data",
     "scites": 356
    },
    {
     "id": "2603.28627",
     "title": "Shor's algorithm is possible with as few as 10,000 reconfigurable atomic qubits",
     "scites": 352
    },
    {
     "id": "2507.11536",
     "title": "Understanding Quantum Information and Computation",
     "scites": 279
    },
    {
     "id": "2605.10943",
     "title": "A passive self-correcting quantum memory in three dimensions",
     "scites": 277
    },
    {
     "id": "2510.19928",
     "title": "Mind the gaps: The fraught road to quantum advantage",
     "scites": 241
    },
    {
     "id": "2508.05720",
     "title": "The vast world of quantum advantage",
     "scites": 235
    },
    {
     "id": "2511.15806",
     "title": "Mixed state tomography reduces to pure state tomography",
     "scites": 224
    },
    {
     "id": "2510.05262",
     "title": "Peaked quantum advantage using error correction",
     "scites": 215
    },
    {
     "id": "2602.11457",
     "title": "The Pinnacle Architecture: Reducing the cost of breaking RSA-2048 to 100 000 physical qubits using quantum LDPC codes",
     "scites": 206
    },
    {
     "id": "2509.07255",
     "title": "Demonstrating an unconditional separation between quantum and classical information resources",
     "scites": 205
    }
   ],
   "keywords": [
    {
     "word": "quantum advantage",
     "papers": 6,
     "scites": 1341,
     "score": 100
    },
    {
     "word": "error correction",
     "papers": 3,
     "scites": 532,
     "score": 45
    },
    {
     "word": "quantum ldpc",
     "papers": 2,
     "scites": 393,
     "score": 31
    },
    {
     "word": "ldpc codes",
     "papers": 2,
     "scites": 393,
     "score": 31
    },
    {
     "word": "fewer gates",
     "papers": 2,
     "scites": 350,
     "score": 30
    },
    {
     "word": "logical qubits",
     "papers": 2,
     "scites": 368,
     "score": 30
    },
    {
     "word": "trapped-ion quantum",
     "papers": 2,
     "scites": 335,
     "score": 29
    },
    {
     "word": "quantum computer",
     "papers": 2,
     "scites": 335,
     "score": 29
    }
   ]
  }
 }
}